{
  "Workflows": [
    {
      "Path": null,
      "SortBy": 0,
      "VariablesSectionElementsOrder": [],
      "ArgumentsSectionElementsOrder": null,
      "ConstantsSectionElementsOrder": [],
      "AddedNamespaces": null
    },
    {
      "Path": "Main.xaml",
      "SortBy": 0,
      "VariablesSectionElementsOrder": [
        "dt_itemData4&Sequence_7",
        "excelFolderPath&Sequence_1",
        "mailContent&Sequence_2",
        "mailTitle&Sequence_2",
        "formatPrice&Sequence_15",
        "formatDiscnt&Sequence_15",
        "dr_minPrice&Sequence_1",
        "minPrice&Sequence_1",
        "maxDiscnt&Sequence_1",
        "dr_maxDiscntItem&Sequence_1",
        "excelFileName&Sequence_1",
        "dt_quiz&Sequence_1",
        "urlLowPrice&Sequence_9",
        "urlSlice&Sequence_9",
        "urlIdx&Sequence_9",
        "dt_detailType&Sequence_7",
        "itemCnt&Sequence_9",
        "idx_depth1&Sequence_1",
        "dt_category2&Sequence_7",
        "dt_category1&Sequence_1"
      ],
      "ArgumentsSectionElementsOrder": [],
      "ConstantsSectionElementsOrder": [],
      "AddedNamespaces": null
    },
    {
      "Path": "Main2.xaml",
      "SortBy": 0,
      "VariablesSectionElementsOrder": [
        "itemCnt&Sequence_8",
        "idx_depth1&Sequence_2",
        "excelFileName&Sequence_1",
        "dt_itemData&Sequence_5",
        "urlLowPrice&Sequence_8",
        "urlSlice&Sequence_8",
        "urlIdx&Sequence_8",
        "dt_category1&Sequence_2",
        "dt_category2&Sequence_5"
      ],
      "ArgumentsSectionElementsOrder": [],
      "ConstantsSectionElementsOrder": [],
      "AddedNamespaces": null
    }
  ]
}